README.md
setup.cfg
setup.py
scaledrone/__init__.py
scaledrone/scaledrone.py
scaledrone.egg-info/PKG-INFO
scaledrone.egg-info/SOURCES.txt
scaledrone.egg-info/dependency_links.txt
scaledrone.egg-info/requires.txt
scaledrone.egg-info/top_level.txt