Metadata-Version: 1.1
Name: scaledrone
Version: 0.2.0
Summary: Official Scaledrone Python API client
Home-page: https://github.com/Scaledrone/scaledrone-python
Author: Serge Herkül
Author-email: info@scaledrone.com
License: MIT
Download-URL: https://github.com/Scaledrone/scaledrone-python/tarball/0.2
Platform: UNKNOWN
Classifier: Development Status :: 5 - Production/Stable
Classifier: Intended Audience :: Developers
Classifier: License :: OSI Approved :: MIT License
Classifier: Operating System :: OS Independent
Classifier: Programming Language :: Python
Classifier: Topic :: Software Development :: Libraries :: Python Modules
